minimal_hubert/__init__.py
minimal_hubert/__main__.py
minimal_hubert/abx.py
minimal_hubert/config.py
minimal_hubert/data.py
minimal_hubert/features.py
minimal_hubert/kmeans.py
minimal_hubert/model.py
minimal_hubert/py.typed
minimal_hubert/train.py
minimal_hubert/transcribe.py
minimal_hubert/validate.py
minimal_hubert/utils/__init__.py
minimal_hubert/utils/best_checkpoint.py
minimal_hubert/utils/distributed.py
minimal_hubert/utils/merge_manifest_with_units.py
minimal_hubert-0.0.2.dist-info/METADATA
minimal_hubert-0.0.2.dist-info/WHEEL
minimal_hubert-0.0.2.dist-info/licenses/LICENSE
minimal_hubert-0.0.2.dist-info/RECORD
