Metadata-Version: 2.4
Name: minimal-hubert
Version: 0.0.2
Summary: Minimal implementation of HuBERT pretraining
Author: Maxime Poli
License-Expression: MIT
License-File: LICENSE
Requires-Python: >=3.12
Requires-Dist: fastabx>=0.6.1
Requires-Dist: filelock>=3.20.2
Requires-Dist: orjson>=3.11.5
Requires-Dist: scikit-learn>=1.8.0
Requires-Dist: spidr[train]>=0.1.3
Requires-Dist: torch>=2.9.1
Requires-Dist: torchaudio>=2.9.1
Requires-Dist: torchcodec>=0.9.1
